{
  "book_id": "ISA",
  "book_name": "Isaiah",
  "chapter": 6,
  "verses": 13,
  "content": [
    {
      "text": "Isaiah’s Commission",
      "type": "heading"
    },
    {
      "text": "In the year that King Uzziah died, I saw the Lord, high and exalted, seated on a throne; and the train of his robe filled the temple.",
      "verse": 1,
      "type": "newline"
    },
    {
      "text": "Above him were seraphim, each with six wings: With two wings they covered their faces, with two they covered their feet, and with two they were flying.",
      "verse": 2
    },
    {
      "text": "And they were calling to one another:",
      "verse": 3
    },
    {
      "text": "“Holy, holy, holy is the Lord Almighty;",
      "verse": 3,
      "type": "poetry newline"
    },
    {
      "text": "the whole earth is full of his glory.”",
      "verse": 3,
      "type": "poetry"
    },
    {
      "text": "At the sound of their voices the doorposts and thresholds shook and the temple was filled with smoke.",
      "verse": 4,
      "type": "newline"
    },
    {
      "text": "“Woe to me!” I cried. “I am ruined! For I am a man of unclean lips, and I live among a people of unclean lips, and my eyes have seen the King, the Lord Almighty.”",
      "verse": 5,
      "type": "newline"
    },
    {
      "text": "Then one of the seraphim flew to me with a live coal in his hand, which he had taken with tongs from the altar.",
      "verse": 6,
      "type": "newline"
    },
    {
      "text": "With it he touched my mouth and said, “See, this has touched your lips; your guilt is taken away and your sin atoned for.”",
      "verse": 7
    },
    {
      "text": "Then I heard the voice of the Lord saying, “Whom shall I send? And who will go for us?”",
      "verse": 8,
      "type": "newline"
    },
    {
      "text": "And I said, “Here am I. Send me!”",
      "verse": 8,
      "type": "newline"
    },
    {
      "text": "He said, “Go and tell this people:",
      "verse": 9,
      "type": "newline"
    },
    {
      "text": "“‘Be ever hearing, but never understanding;",
      "verse": 9,
      "type": "poetry newline"
    },
    {
      "text": "be ever seeing, but never perceiving.’",
      "verse": 9,
      "type": "poetry"
    },
    {
      "text": "Make the heart of this people calloused;",
      "verse": 10,
      "type": "poetry"
    },
    {
      "text": "make their ears dull",
      "verse": 10,
      "type": "poetry"
    },
    {
      "text": "and close their eyes.",
      "verse": 10,
      "type": "poetry"
    },
    {
      "text": "Otherwise they might see with their eyes,",
      "verse": 10,
      "type": "poetry"
    },
    {
      "text": "hear with their ears,",
      "verse": 10,
      "type": "poetry"
    },
    {
      "text": "understand with their hearts,",
      "verse": 10,
      "type": "poetry"
    },
    {
      "text": "and turn and be healed.”",
      "verse": 10,
      "type": "poetry"
    },
    {
      "text": "Then I said, “For how long, Lord?”",
      "verse": 11,
      "type": "newline"
    },
    {
      "text": "And he answered:",
      "verse": 11,
      "type": "newline"
    },
    {
      "text": "“Until the cities lie ruined",
      "verse": 11,
      "type": "poetry newline"
    },
    {
      "text": "and without inhabitant,",
      "verse": 11,
      "type": "poetry"
    },
    {
      "text": "until the houses are left deserted",
      "verse": 11,
      "type": "poetry"
    },
    {
      "text": "and the fields ruined and ravaged,",
      "verse": 11,
      "type": "poetry"
    },
    {
      "text": "until the Lord has sent everyone far away",
      "verse": 12,
      "type": "poetry"
    },
    {
      "text": "and the land is utterly forsaken.",
      "verse": 12,
      "type": "poetry"
    },
    {
      "text": "And though a tenth remains in the land,",
      "verse": 13,
      "type": "poetry"
    },
    {
      "text": "it will again be laid waste.",
      "verse": 13,
      "type": "poetry"
    },
    {
      "text": "But as the terebinth and oak",
      "verse": 13,
      "type": "poetry"
    },
    {
      "text": "leave stumps when they are cut down,",
      "verse": 13,
      "type": "poetry"
    },
    {
      "text": "so the holy seed will be the stump in the land.”",
      "verse": 13,
      "type": "poetry"
    }
  ]
}