{
  "book_id": "PS",
  "book_name": "Psalm",
  "chapter": 110,
  "verses": 7,
  "content": [
    {
      "text": "Sit at My Right Hand",
      "type": "heading"
    },
    {
      "text": "A Psalm of David.",
      "type": "title"
    },
    {
      "text": "The Lord says to my Lord:",
      "verse": 1,
      "type": "poetry newline"
    },
    {
      "text": "“Sit at my right hand,",
      "verse": 1,
      "type": "poetry"
    },
    {
      "text": "until I make your enemies your footstool.”",
      "verse": 1,
      "type": "poetry"
    },
    {
      "text": "The Lord sends forth from Zion",
      "verse": 2,
      "type": "poetry newline"
    },
    {
      "text": "your mighty scepter.",
      "verse": 2,
      "type": "poetry"
    },
    {
      "text": "Rule in the midst of your enemies!",
      "verse": 2,
      "type": "poetry"
    },
    {
      "text": "Your people will offer themselves freely",
      "verse": 3,
      "type": "poetry"
    },
    {
      "text": "on the day of your power,",
      "verse": 3,
      "type": "poetry"
    },
    {
      "text": "in holy garments;",
      "verse": 3,
      "type": "poetry"
    },
    {
      "text": "from the womb of the morning,",
      "verse": 3,
      "type": "poetry"
    },
    {
      "text": "the dew of your youth will be yours.",
      "verse": 3,
      "type": "poetry"
    },
    {
      "text": "The Lord has sworn",
      "verse": 4,
      "type": "poetry"
    },
    {
      "text": "and will not change his mind,",
      "verse": 4,
      "type": "poetry"
    },
    {
      "text": "“You are a priest forever",
      "verse": 4,
      "type": "poetry"
    },
    {
      "text": "after the order of Melchizedek.”",
      "verse": 4,
      "type": "poetry"
    },
    {
      "text": "The Lord is at your right hand;",
      "verse": 5,
      "type": "poetry newline"
    },
    {
      "text": "he will shatter kings on the day of his wrath.",
      "verse": 5,
      "type": "poetry"
    },
    {
      "text": "He will execute judgment among the nations,",
      "verse": 6,
      "type": "poetry"
    },
    {
      "text": "filling them with corpses;",
      "verse": 6,
      "type": "poetry"
    },
    {
      "text": "he will shatter chiefs",
      "verse": 6,
      "type": "poetry"
    },
    {
      "text": "over the wide earth.",
      "verse": 6,
      "type": "poetry"
    },
    {
      "text": "He will drink from the brook by the way;",
      "verse": 7,
      "type": "poetry"
    },
    {
      "text": "therefore he will lift up his head.",
      "verse": 7,
      "type": "poetry"
    }
  ]
}