{
  "book_id": "PS",
  "book_name": "Psalm",
  "chapter": 34,
  "verses": 22,
  "content": [
    {
      "text": "Taste and See That the Lord Is Good",
      "type": "heading"
    },
    {
      "text": " Of David, when he changed his behavior before Abimelech, so that he drove him out, and he went away.",
      "type": "title"
    },
    {
      "text": "I will bless the Lord at all times;",
      "verse": 1,
      "type": "poetry newline"
    },
    {
      "text": "his praise shall continually be in my mouth.",
      "verse": 1,
      "type": "poetry"
    },
    {
      "text": "My soul makes its boast in the Lord;",
      "verse": 2,
      "type": "poetry"
    },
    {
      "text": "let the humble hear and be glad.",
      "verse": 2,
      "type": "poetry"
    },
    {
      "text": "Oh, magnify the Lord with me,",
      "verse": 3,
      "type": "poetry"
    },
    {
      "text": "and let us exalt his name together!",
      "verse": 3,
      "type": "poetry"
    },
    {
      "text": "I sought the Lord, and he answered me",
      "verse": 4,
      "type": "poetry newline"
    },
    {
      "text": "and delivered me from all my fears.",
      "verse": 4,
      "type": "poetry"
    },
    {
      "text": "Those who look to him are radiant,",
      "verse": 5,
      "type": "poetry"
    },
    {
      "text": "and their faces shall never be ashamed.",
      "verse": 5,
      "type": "poetry"
    },
    {
      "text": "This poor man cried, and the Lord heard him",
      "verse": 6,
      "type": "poetry"
    },
    {
      "text": "and saved him out of all his troubles.",
      "verse": 6,
      "type": "poetry"
    },
    {
      "text": "The angel of the Lord encamps",
      "verse": 7,
      "type": "poetry"
    },
    {
      "text": "around those who fear him, and delivers them.",
      "verse": 7,
      "type": "poetry"
    },
    {
      "text": "Oh, taste and see that the Lord is good!",
      "verse": 8,
      "type": "poetry newline"
    },
    {
      "text": "Blessed is the man who takes refuge in him!",
      "verse": 8,
      "type": "poetry"
    },
    {
      "text": "Oh, fear the Lord, you his saints,",
      "verse": 9,
      "type": "poetry"
    },
    {
      "text": "for those who fear him have no lack!",
      "verse": 9,
      "type": "poetry"
    },
    {
      "text": "The young lions suffer want and hunger;",
      "verse": 10,
      "type": "poetry"
    },
    {
      "text": "but those who seek the Lord lack no good thing.",
      "verse": 10,
      "type": "poetry"
    },
    {
      "text": "Come, O children, listen to me;",
      "verse": 11,
      "type": "poetry newline"
    },
    {
      "text": "I will teach you the fear of the Lord.",
      "verse": 11,
      "type": "poetry"
    },
    {
      "text": "What man is there who desires life",
      "verse": 12,
      "type": "poetry"
    },
    {
      "text": "and loves many days, that he may see good?",
      "verse": 12,
      "type": "poetry"
    },
    {
      "text": "Keep your tongue from evil",
      "verse": 13,
      "type": "poetry"
    },
    {
      "text": "and your lips from speaking deceit.",
      "verse": 13,
      "type": "poetry"
    },
    {
      "text": "Turn away from evil and do good;",
      "verse": 14,
      "type": "poetry"
    },
    {
      "text": "seek peace and pursue it.",
      "verse": 14,
      "type": "poetry"
    },
    {
      "text": "The eyes of the Lord are toward the righteous",
      "verse": 15,
      "type": "poetry newline"
    },
    {
      "text": "and his ears toward their cry.",
      "verse": 15,
      "type": "poetry"
    },
    {
      "text": "The face of the Lord is against those who do evil,",
      "verse": 16,
      "type": "poetry"
    },
    {
      "text": "to cut off the memory of them from the earth.",
      "verse": 16,
      "type": "poetry"
    },
    {
      "text": "When the righteous cry for help, the Lord hears",
      "verse": 17,
      "type": "poetry"
    },
    {
      "text": "and delivers them out of all their troubles.",
      "verse": 17,
      "type": "poetry"
    },
    {
      "text": "The Lord is near to the brokenhearted",
      "verse": 18,
      "type": "poetry"
    },
    {
      "text": "and saves the crushed in spirit.",
      "verse": 18,
      "type": "poetry"
    },
    {
      "text": "Many are the afflictions of the righteous,",
      "verse": 19,
      "type": "poetry newline"
    },
    {
      "text": "but the Lord delivers him out of them all.",
      "verse": 19,
      "type": "poetry"
    },
    {
      "text": "He keeps all his bones;",
      "verse": 20,
      "type": "poetry"
    },
    {
      "text": "not one of them is broken.",
      "verse": 20,
      "type": "poetry"
    },
    {
      "text": "Affliction will slay the wicked,",
      "verse": 21,
      "type": "poetry"
    },
    {
      "text": "and those who hate the righteous will be condemned.",
      "verse": 21,
      "type": "poetry"
    },
    {
      "text": "The Lord redeems the life of his servants;",
      "verse": 22,
      "type": "poetry"
    },
    {
      "text": "none of those who take refuge in him will be condemned.",
      "verse": 22,
      "type": "poetry"
    }
  ]
}